Metadata-Version: 1.0
Name: toil-nanopore
Version: 0.2.30
Summary: Toil-script for performing MinION sequence analysis
Home-page: https://github.com/ArtRand/toil-marginAlign
Author: Benedict Paten and Art Rand
Author-email: benedict@soe.ucsc.edu, arand@soe.ucsc.edu
License: UNKNOWN
Platform: UNKNOWN
